tronyx/__init__.py
tronyx/abi.py
tronyx/async_contract.py
tronyx/async_tron.py
tronyx/contract.py
tronyx/defaults.py
tronyx/exceptions.py
tronyx/tron.py
tronyx/version.py
tronyx/hdwallet/__init__.py
tronyx/hdwallet/_utils.py
tronyx/hdwallet/deterministic.py
tronyx/keys/__init__.py
tronyx/providers/__init__.py
tronyx/providers/async_http.py
tronyx/providers/http.py
tronyx-0.5.1.dist-info/LICENSE
tronyx-0.5.1.dist-info/METADATA
tronyx-0.5.1.dist-info/WHEEL
tronyx-0.5.1.dist-info/top_level.txt
tronyx-0.5.1.dist-info/RECORD
