Metadata-Version: 2.1
Name: tronyx
Version: 0.5.1
Summary: TRON Python client library
Home-page: https://github.com/andelf/tronyx
Author: andelf
Author-email: andelf@gmail.com
Requires-Python: >=3.8
License-File: LICENSE
Requires-Dist: base58
Requires-Dist: coincurve
Requires-Dist: eth-abi (<6.0.0,>=5.0.0)
Requires-Dist: httpx
Requires-Dist: pycryptodome (<4)
Requires-Dist: requests
Provides-Extra: mnemonic
Requires-Dist: mnemonic (==0.20) ; extra == 'mnemonic'
